EduSocialMediaDSHelper/__init__.py
EduSocialMediaDSHelper/create_cars_dataset.py
EduSocialMediaDSHelper/create_sphinx_data.py
EduSocialMediaDSHelper/create_twitter_dataset.py
EduSocialMediaDSHelper/create_uci_census_data.py
EduSocialMediaDSHelper/create_video_games_dataset.py
EduSocialMediaDSHelper/element_answer_checks.py
EduSocialMediaDSHelper/list_answer_checks.py
EduSocialMediaDSHelper/load_legos.py
EduSocialMediaDSHelper/misc_helpers.py
EduSocialMediaDSHelper/recommender_support.py
EduSocialMediaDSHelper/legos/color_counts.csv
EduSocialMediaDSHelper/legos/sets.csv
EduSocialMediaDSHelper-0.1.1.dist-info/LICENSE.md
EduSocialMediaDSHelper-0.1.1.dist-info/METADATA
EduSocialMediaDSHelper-0.1.1.dist-info/WHEEL
EduSocialMediaDSHelper-0.1.1.dist-info/top_level.txt
EduSocialMediaDSHelper-0.1.1.dist-info/RECORD
