Metadata-Version: 2.1
Name: EduSocialMediaDSHelper
Version: 0.1.1
Summary: Helper for DS Social Media learning material
Home-page: https://github.com/Joshkking/EduSocialMediaDSHelper
Author: Josh King
Author-email: joshkking@gmail.com
Classifier: Programming Language :: Python :: 3
Classifier: License :: OSI Approved :: MIT License
Classifier: Operating System :: OS Independent
Requires-Python: >=3.6
License-File: LICENSE.md
